even_or_odd_ebin-0.1.5.dist-info/licenses/LICENSE
odd_or_even/__init__.py
odd_or_even/core.py
even_or_odd_ebin-0.1.5.dist-info/METADATA
even_or_odd_ebin-0.1.5.dist-info/WHEEL
even_or_odd_ebin-0.1.5.dist-info/top_level.txt
even_or_odd_ebin-0.1.5.dist-info/RECORD
