Metadata-Version: 2.4
Name: even-or-odd-ebin
Version: 0.1.5
Summary: Small helper to check whether a number is even or odd.
Author-email: Ebin Louis <ebinlouis1559@gmail.com>
License: MIT
Keywords: even,odd,numbers,utility
Classifier: Programming Language :: Python :: 3
Classifier: License :: OSI Approved :: MIT License
Classifier: Operating System :: OS Independent
Requires-Python: >=3.8
License-File: LICENSE
Dynamic: license-file
